bitarray/__init__.py
bitarray/_bitarray.cpython-37m-darwin.so
bitarray/_util.cpython-37m-darwin.so
bitarray/test_bitarray.py
bitarray/test_util.py
bitarray/util.py
bitarray_ph4-1.6.3.dist-info/AUTHORS
bitarray_ph4-1.6.3.dist-info/LICENSE
bitarray_ph4-1.6.3.dist-info/METADATA
bitarray_ph4-1.6.3.dist-info/WHEEL
bitarray_ph4-1.6.3.dist-info/top_level.txt
bitarray_ph4-1.6.3.dist-info/RECORD
