Metadata-Version: 2.1
Name: bitarray-ph4
Version: 1.6.3
Summary: efficient arrays of booleans -- C extension
Home-page: https://github.com/ph4r05/bitarray
Author: Ilan Schnell
Author-email: ilanschnell@gmail.com
Maintainer: Dusan Klinec (ph4r05)
Maintainer-email: dusan.klinec@gmail.com
License: PSF
Platform: UNKNOWN
Classifier: License :: OSI Approved :: Python Software Foundation License
Classifier: Development Status :: 5 - Production/Stable
Classifier: Intended Audience :: Developers
Classifier: Operating System :: OS Independent
Classifier: Programming Language :: C
Classifier: Programming Language :: Python :: 2
Classifier: Programming Language :: Python :: 2.7
Classifier: Programming Language :: Python :: 3
Classifier: Programming Language :: Python :: 3.5
Classifier: Programming Language :: Python :: 3.6
Classifier: Programming Language :: Python :: 3.7
Classifier: Programming Language :: Python :: 3.8
Classifier: Programming Language :: Python :: 3.9
Classifier: Programming Language :: Python :: 3.10
Classifier: Topic :: Utilities
